README.md
setup.py
src/decorated/__init__.py
src/decorated/testing.py
src/decorated.egg-info/PKG-INFO
src/decorated.egg-info/SOURCES.txt
src/decorated.egg-info/dependency_links.txt
src/decorated.egg-info/requires.txt
src/decorated.egg-info/top_level.txt
src/decorated/base/__init__.py
src/decorated/base/context.py
src/decorated/base/dict.py
src/decorated/base/expression.py
src/decorated/base/false.py
src/decorated/base/function.py
src/decorated/base/proxy.py
src/decorated/base/template.py
src/decorated/base/thread_local.py
src/decorated/decorators/__init__.py
src/decorated/decorators/cache.py
src/decorated/decorators/conditional.py
src/decorated/decorators/events.py
src/decorated/decorators/files.py
src/decorated/decorators/locks.py
src/decorated/decorators/once.py
src/decorated/decorators/probability.py
src/decorated/decorators/profile.py
src/decorated/decorators/remove_extra_args.py
src/decorated/decorators/retries.py
src/decorated/decorators/timeit.py
src/decorated/decorators/timeout.py
src/decorated/decorators/validations/__init__.py
src/decorated/decorators/validations/engine.py
src/decorated/decorators/validations/errors.py
src/decorated/decorators/validations/validators/__init__.py
src/decorated/decorators/validations/validators/base.py
src/decorated/decorators/validations/validators/misc.py
src/decorated/decorators/validations/validators/number.py
src/decorated/decorators/validations/validators/string.py
src/decorated/util/__init__.py
src/decorated/util/dutil.py
src/decorated/util/gcutil.py
src/decorated/util/modutil.py
src/decorated/util/reporters.py
test/testing_test.py
test/testutil.py