Metadata-Version: 2.1
Name: decorated
Version: 1.9.8
Summary: Decorator framework and common decorators for python.
Home-page: https://github.com/cooledcoffee/decorated
Author: Mengchen LEE
License: UNKNOWN
Platform: UNKNOWN
Classifier: Development Status :: 4 - Beta
Classifier: Intended Audience :: Developers
Classifier: Operating System :: OS Independent
Classifier: Programming Language :: Python
Classifier: Programming Language :: Python :: 2
Classifier: Programming Language :: Python :: 3
Classifier: Topic :: Software Development :: Libraries
Provides-Extra: test
